micro_app.py
micro_registry/__init__.py
micro_registry/component.py
micro_registry/component_loader.py
micro_registry/component_rest_api.py
micro_registry/console_interface.py
micro_registry/executor.py
micro_registry/registry.py
micro_registry/registry_rest_api.py
micro_registry-0.4.3.dist-info/LICENSE
micro_registry-0.4.3.dist-info/METADATA
micro_registry-0.4.3.dist-info/WHEEL
micro_registry-0.4.3.dist-info/entry_points.txt
micro_registry-0.4.3.dist-info/RECORD
