Metadata-Version: 2.1
Name: micro-registry
Version: 0.4.3
Summary: A Python library for managing and loading class instances from modules and YAML configurations.
License: MIT
Author: Aleksander Stanik
Author-email: aleksander.stanik@hammerheadesengineers.com
Requires-Python: >=3.7,<4.0
Classifier: License :: OSI Approved :: MIT License
Classifier: Programming Language :: Python :: 3
Classifier: Programming Language :: Python :: 3.7
Classifier: Programming Language :: Python :: 3.8
Classifier: Programming Language :: Python :: 3.9
Classifier: Programming Language :: Python :: 3.10
Classifier: Programming Language :: Python :: 3.11
Classifier: Programming Language :: Python :: 3.12
Classifier: Programming Language :: Python :: 3.13
Requires-Dist: PyYAML
Requires-Dist: fastapi
Requires-Dist: httpx
Requires-Dist: uvicorn
